{
  "version": "7",
  "dialect": "postgresql",
  "entries": [
    {
      "idx": 0,
      "version": "7",
      "when": 1755197993402,
      "tag": "0000_ancient_ares",
      "breakpoints": true
    },
    {
      "idx": 1,
      "version": "7",
      "when": 1755447664292,
      "tag": "0001_lying_reaper",
      "breakpoints": true
    },
    {
      "idx": 2,
      "version": "7",
      "when": 1755524161990,
      "tag": "0002_volatile_risque",
      "breakpoints": true
    },
    {
      "idx": 3,
      "version": "7",
      "when": 1757347103040,
      "tag": "0003_parched_hiroim",
      "breakpoints": true
    },
    {
      "idx": 4,
      "version": "7",
      "when": 1759764536346,
      "tag": "0004_silent_vulture",
      "breakpoints": true
    },
    {
      "idx": 5,
      "version": "7",
      "when": 1759849073872,
      "tag": "0005_majestic_hellcat",
      "breakpoints": true
    },
    {
      "idx": 6,
      "version": "7",
      "when": 1759864151367,
      "tag": "0006_cloudy_carmella_unuscione",
      "breakpoints": true
    },
    {
      "idx": 7,
      "version": "7",
      "when": 1759864431598,
      "tag": "0007_milky_felicia_hardy",
      "breakpoints": true
    },
    {
      "idx": 8,
      "version": "7",
      "when": 1760021002789,
      "tag": "0008_cold_marvex",
      "breakpoints": true
    },
    {
      "idx": 9,
      "version": "7",
      "when": 1760102608313,
      "tag": "0009_thick_mastermind",
      "breakpoints": true
    },
    {
      "idx": 10,
      "version": "7",
      "when": 1760104630419,
      "tag": "0010_striped_zombie",
      "breakpoints": true
    },
    {
      "idx": 11,
      "version": "7",
      "when": 1760122913243,
      "tag": "0011_tough_scalphunter",
      "breakpoints": true
    }
  ]
}